pytusm/__init__.py
pytusm/tusm.py
pytusm-0.0.4.dist-info/METADATA
pytusm-0.0.4.dist-info/WHEEL
pytusm-0.0.4.dist-info/licenses/LICENSE
pytusm-0.0.4.dist-info/RECORD
